[
	{
		"name": "Templar Knight",
		"unitType": "Mounted",
		"movement": 4,
		"strength": 28,
		"cost": 200,
		"requiredTech": "Chivalry",
		"obsoleteTech": "Military Science",
		"upgradesTo": "Cavalry",
		"requiredResource": "Horses",
		"uniques": ["Can move after attacking","No defensive terrain bonus","[-33]% Strength <vs cities> <when attacking>", "Never appears as a Barbarian unit"],
		"attackSound": "horse"
	},
	{
		"name": "Hospitaller Knight",
		"unitType": "Mounted",
		"movement": 4,
		"strength": 28,
		"cost": 200,
		"requiredTech": "Chivalry",
		"obsoleteTech": "Military Science",
		"upgradesTo": "Cavalry",
		"requiredResource": "Horses",
		"uniques": ["Can move after attacking","No defensive terrain bonus","[-33]% Strength <vs cities> <when attacking>", "Never appears as a Barbarian unit"],
		"attackSound": "horse"
	},
		{
		"name": "Knight of Santiago",
		"unitType": "Mounted",
		"movement": 4,
		"strength": 28,
		"cost": 200,
		"requiredTech": "Chivalry",
		"obsoleteTech": "Military Science",
		"upgradesTo": "Cavalry",
		"requiredResource": "Horses",
		"uniques": ["Can move after attacking","No defensive terrain bonus","[-33]% Strength <vs cities> <when attacking>", "Never appears as a Barbarian unit"],
		"attackSound": "horse"
	},
		{
		"name": "Teutonic Knight",
		"unitType": "Mounted",
		"movement": 4,
		"strength": 28,
		"cost": 200,
		"requiredTech": "Chivalry",
		"obsoleteTech": "Military Science",
		"upgradesTo": "Cavalry",
		"requiredResource": "Horses",
		"uniques": ["Can move after attacking","No defensive terrain bonus","[-33]% Strength <vs cities> <when attacking>", "Never appears as a Barbarian unit"],
		"attackSound": "horse"
	},
		{
		"name": "Livonian Knight",
		"unitType": "Mounted",
		"movement": 4,
		"strength": 28,
		"cost": 200,
		"requiredTech": "Chivalry",
		"obsoleteTech": "Military Science",
		"upgradesTo": "Cavalry",
		"requiredResource": "Horses",
		"uniques": ["Can move after attacking","No defensive terrain bonus","[-33]% Strength <vs cities> <when attacking>", "Never appears as a Barbarian unit"],
		"attackSound": "horse"
	}
]
